carveme_gut/.DS_Store
carveme_gut/__init__.py
carveme_gut/cli/__init__.py
carveme_gut/cli/benchmark.py
carveme_gut/cli/benchmark_cdiff.py
carveme_gut/cli/benchmark_new.py
carveme_gut/cli/build_universe.py
carveme_gut/cli/carve.py
carveme_gut/cli/carve.py~
carveme_gut/cli/curate_universe.py
carveme_gut/cli/gapfill.py
carveme_gut/cli/merge_community.py
carveme_gut/cli/original_carve.py
carveme_gut/config.cfg
carveme_gut/reconstruction/__init__.py
carveme_gut/reconstruction/benchmark.py
carveme_gut/reconstruction/carving.py
carveme_gut/reconstruction/diamond.py
carveme_gut/reconstruction/eggnog.py
carveme_gut/reconstruction/gapfilling.py
carveme_gut/reconstruction/ncbi_download.py
carveme_gut/reconstruction/scoring.py
carveme_gut/reconstruction/scoring_old.py
carveme_gut/reconstruction/utils.py
carveme_gut/universe/__init__.py
carveme_gut/universe/annotate.py
carveme_gut/universe/curation.py
carveme_gut/universe/download.py
carveme_gut-0.1.0.dist-info/METADATA
carveme_gut-0.1.0.dist-info/WHEEL
carveme_gut-0.1.0.dist-info/RECORD
